{
  "retrieved_at": "2026-06-03T00:27:36.863184",
  "data": {
    "美股指數ETF": [
      {
        "symbol": "^DJI",
        "regularMarketPrice": null,
        "currency": "USD",
        "exchange": "DJI",
        "regularMarketChange": null,
        "regularMarketChangePercent": null,
        "regularMarketPreviousClose": null,
        "regularMarketOpen": 50912.83984375,
        "regularMarketDayHigh": null,
        "regularMarketDayLow": null,
        "timestamp": "2026-06-03T00:27:37.826326",
        "name": "道瓊指數 (DJI)"
      },
      {
        "symbol": "^NDX",
        "regularMarketPrice": null,
        "currency": "USD",
        "exchange": "NIM",
        "regularMarketChange": null,
        "regularMarketChangePercent": null,
        "regularMarketPreviousClose": null,
        "regularMarketOpen": 30471.61328125,
        "regularMarketDayHigh": null,
        "regularMarketDayLow": null,
        "timestamp": "2026-06-03T00:27:38.391326",
        "name": "那斯達克 100 (NDQ)"
      },
      {
        "symbol": "SPY",
        "regularMarketPrice": 759.57,
        "currency": "USD",
        "exchange": "PCX",
        "regularMarketChange": null,
        "regularMarketChangePercent": null,
        "regularMarketPreviousClose": 758.54,
        "regularMarketOpen": 757.03,
        "regularMarketDayHigh": null,
        "regularMarketDayLow": null,
        "timestamp": "2026-06-03T00:27:39.322064",
        "name": "SPY (標普 500 ETF)"
      },
      {
        "symbol": "VOO",
        "regularMarketPrice": 698.26,
        "currency": "USD",
        "exchange": "PCX",
        "regularMarketChange": null,
        "regularMarketChangePercent": null,
        "regularMarketPreviousClose": 697.3,
        "regularMarketOpen": 696.06,
        "regularMarketDayHigh": null,
        "regularMarketDayLow": null,
        "timestamp": "2026-06-03T00:27:40.139273",
        "name": "VOO (Vanguard S&P 500 ETF)"
      },
      {
        "symbol": "VTI",
        "regularMarketPrice": 374.36,
        "currency": "USD",
        "exchange": "PCX",
        "regularMarketChange": null,
        "regularMarketChangePercent": null,
        "regularMarketPreviousClose": 373.4,
        "regularMarketOpen": 372.88,
        "regularMarketDayHigh": null,
        "regularMarketDayLow": null,
        "timestamp": "2026-06-03T00:27:40.696914",
        "name": "VTI (Vanguard Total Stock Market)"
      },
      {
        "symbol": "QQQ",
        "regularMarketPrice": 746.16,
        "currency": "USD",
        "exchange": "NGM",
        "regularMarketChange": null,
        "regularMarketChangePercent": null,
        "regularMarketPreviousClose": 742.74,
        "regularMarketOpen": 742.4,
        "regularMarketDayHigh": null,
        "regularMarketDayLow": null,
        "timestamp": "2026-06-03T00:27:41.350448",
        "name": "QQQ (Invesco QQQ Trust)"
      }
    ],
    "美股個股 (科技+半導體)": [
      {
        "symbol": "NVDA",
        "regularMarketPrice": 222.82,
        "currency": "USD",
        "exchange": "NMS",
        "regularMarketChange": null,
        "regularMarketChangePercent": null,
        "regularMarketPreviousClose": 224.36,
        "regularMarketOpen": 227.18,
        "regularMarketDayHigh": null,
        "regularMarketDayLow": null,
        "timestamp": "2026-06-03T00:27:41.930527",
        "name": "輝達 (NVDA)"
      },
      {
        "symbol": "AMD",
        "regularMarketPrice": 521.54,
        "currency": "USD",
        "exchange": "NMS",
        "regularMarketChange": null,
        "regularMarketChangePercent": null,
        "regularMarketPreviousClose": 510.13,
        "regularMarketOpen": 506.3,
        "regularMarketDayHigh": null,
        "regularMarketDayLow": null,
        "timestamp": "2026-06-03T00:27:42.604142",
        "name": "AMD"
      },
      {
        "symbol": "AVGO",
        "regularMarketPrice": 481.57,
        "currency": "USD",
        "exchange": "NMS",
        "regularMarketChange": null,
        "regularMarketChangePercent": null,
        "regularMarketPreviousClose": 459.97,
        "regularMarketOpen": 488.79,
        "regularMarketDayHigh": null,
        "regularMarketDayLow": null,
        "timestamp": "2026-06-03T00:27:43.205264",
        "name": "博通 (AVGO)"
      },
      {
        "symbol": "MU",
        "regularMarketPrice": 1064.1,
        "currency": "USD",
        "exchange": "NMS",
        "regularMarketChange": null,
        "regularMarketChangePercent": null,
        "regularMarketPreviousClose": 1035.5,
        "regularMarketOpen": 1050,
        "regularMarketDayHigh": null,
        "regularMarketDayLow": null,
        "timestamp": "2026-06-03T00:27:43.815517",
        "name": "美光 (MU)"
      },
      {
        "symbol": "TSLA",
        "regularMarketPrice": 423.74,
        "currency": "USD",
        "exchange": "NMS",
        "regularMarketChange": null,
        "regularMarketChangePercent": null,
        "regularMarketPreviousClose": 415.88,
        "regularMarketOpen": 418.22,
        "regularMarketDayHigh": null,
        "regularMarketDayLow": null,
        "timestamp": "2026-06-03T00:27:44.391303",
        "name": "特斯拉 (TSLA)"
      },
      {
        "symbol": "TSM",
        "regularMarketPrice": 446.69,
        "currency": "USD",
        "exchange": "NYQ",
        "regularMarketChange": null,
        "regularMarketChangePercent": null,
        "regularMarketPreviousClose": 435.63,
        "regularMarketOpen": 440.58,
        "regularMarketDayHigh": null,
        "regularMarketDayLow": null,
        "timestamp": "2026-06-03T00:27:45.080801",
        "name": "台積電 (TSM)"
      },
      {
        "symbol": "CRWV",
        "regularMarketPrice": 119.27,
        "currency": "USD",
        "exchange": "NMS",
        "regularMarketChange": null,
        "regularMarketChangePercent": null,
        "regularMarketPreviousClose": 124.82,
        "regularMarketOpen": 129.96,
        "regularMarketDayHigh": null,
        "regularMarketDayLow": null,
        "timestamp": "2026-06-03T00:27:45.557654",
        "name": "Crossriver Technologies (CRWV)"
      },
      {
        "symbol": "RKLB",
        "regularMarketPrice": 123.32,
        "currency": "USD",
        "exchange": "NMS",
        "regularMarketChange": null,
        "regularMarketChangePercent": null,
        "regularMarketPreviousClose": 122.39,
        "regularMarketOpen": 125.34,
        "regularMarketDayHigh": null,
        "regularMarketDayLow": null,
        "timestamp": "2026-06-03T00:27:46.064412",
        "name": "Rokla (RKLB)"
      },
      {
        "symbol": "AMZN",
        "regularMarketPrice": 256.52,
        "currency": "USD",
        "exchange": "NMS",
        "regularMarketChange": null,
        "regularMarketChangePercent": null,
        "regularMarketPreviousClose": 261.26,
        "regularMarketOpen": 257.16,
        "regularMarketDayHigh": null,
        "regularMarketDayLow": null,
        "timestamp": "2026-06-03T00:27:46.532638",
        "name": "亞馬遜 (AMZN)"
      },
      {
        "symbol": "SNDK",
        "regularMarketPrice": 1716.36,
        "currency": "USD",
        "exchange": "NMS",
        "regularMarketChange": null,
        "regularMarketChangePercent": null,
        "regularMarketPreviousClose": 1761.43,
        "regularMarketOpen": 1750.06,
        "regularMarketDayHigh": null,
        "regularMarketDayLow": null,
        "timestamp": "2026-06-03T00:27:47.050946",
        "name": "Sandisk (SNDK)"
      },
      {
        "symbol": "AAPL",
        "regularMarketPrice": 315.2,
        "currency": "USD",
        "exchange": "NMS",
        "regularMarketChange": null,
        "regularMarketChangePercent": null,
        "regularMarketPreviousClose": 306.31,
        "regularMarketOpen": 307.46,
        "regularMarketDayHigh": null,
        "regularMarketDayLow": null,
        "timestamp": "2026-06-03T00:27:47.796621",
        "name": "蘋果 (AAPL)"
      },
      {
        "symbol": "ORCL",
        "regularMarketPrice": 244.58,
        "currency": "USD",
        "exchange": "NYQ",
        "regularMarketChange": null,
        "regularMarketChangePercent": null,
        "regularMarketPreviousClose": 248.15,
        "regularMarketOpen": 242.8,
        "regularMarketDayHigh": null,
        "regularMarketDayLow": null,
        "timestamp": "2026-06-03T00:27:48.332267",
        "name": "甲骨文 (ORCL)"
      },
      {
        "symbol": "ARM",
        "regularMarketPrice": 402.71,
        "currency": "USD",
        "exchange": "NMS",
        "regularMarketChange": null,
        "regularMarketChangePercent": null,
        "regularMarketPreviousClose": 408.85,
        "regularMarketOpen": 401.13,
        "regularMarketDayHigh": null,
        "regularMarketDayLow": null,
        "timestamp": "2026-06-03T00:27:48.865626",
        "name": "Arm (ARM)"
      },
      {
        "symbol": "GOOG",
        "regularMarketPrice": 358.39,
        "currency": "USD",
        "exchange": "NMS",
        "regularMarketChange": null,
        "regularMarketChangePercent": null,
        "regularMarketPreviousClose": 372.58,
        "regularMarketOpen": 363.16,
        "regularMarketDayHigh": null,
        "regularMarketDayLow": null,
        "timestamp": "2026-06-03T00:27:49.391608",
        "name": "谷歌 (GOOG)"
      },
      {
        "symbol": "META",
        "regularMarketPrice": 597.63,
        "currency": "USD",
        "exchange": "NMS",
        "regularMarketChange": null,
        "regularMarketChangePercent": null,
        "regularMarketPreviousClose": 600.47,
        "regularMarketOpen": 603.24,
        "regularMarketDayHigh": null,
        "regularMarketDayLow": null,
        "timestamp": "2026-06-03T00:27:49.962900",
        "name": "Meta (META)"
      },
      {
        "symbol": "MSFT",
        "regularMarketPrice": 441.31,
        "currency": "USD",
        "exchange": "NMS",
        "regularMarketChange": null,
        "regularMarketChangePercent": null,
        "regularMarketPreviousClose": 460.52,
        "regularMarketOpen": 446.88,
        "regularMarketDayHigh": null,
        "regularMarketDayLow": null,
        "timestamp": "2026-06-03T00:27:50.536871",
        "name": "微軟 (MSFT)"
      },
      {
        "symbol": "PLTR",
        "regularMarketPrice": 152.17,
        "currency": "USD",
        "exchange": "NMS",
        "regularMarketChange": null,
        "regularMarketChangePercent": null,
        "regularMarketPreviousClose": 160.65,
        "regularMarketOpen": 156.69,
        "regularMarketDayHigh": null,
        "regularMarketDayLow": null,
        "timestamp": "2026-06-03T00:27:51.109181",
        "name": "Palantir (PLTR)"
      },
      {
        "symbol": "ASML",
        "regularMarketPrice": 1705.37,
        "currency": "USD",
        "exchange": "NMS",
        "regularMarketChange": null,
        "regularMarketChangePercent": null,
        "regularMarketPreviousClose": 1628.57,
        "regularMarketOpen": 1659.69,
        "regularMarketDayHigh": null,
        "regularMarketDayLow": null,
        "timestamp": "2026-06-03T00:27:51.834982",
        "name": "ASML"
      },
      {
        "symbol": "COST",
        "regularMarketPrice": 954.27,
        "currency": "USD",
        "exchange": "NMS",
        "regularMarketChange": null,
        "regularMarketChangePercent": null,
        "regularMarketPreviousClose": 946.11,
        "regularMarketOpen": 942.29,
        "regularMarketDayHigh": null,
        "regularMarketDayLow": null,
        "timestamp": "2026-06-03T00:27:52.441688",
        "name": "Costco (COST)"
      },
      {
        "symbol": "MRVL",
        "regularMarketPrice": 290.79,
        "currency": "USD",
        "exchange": "NMS",
        "regularMarketChange": null,
        "regularMarketChangePercent": null,
        "regularMarketPreviousClose": 219.43,
        "regularMarketOpen": 253.46,
        "regularMarketDayHigh": null,
        "regularMarketDayLow": null,
        "timestamp": "2026-06-03T00:27:52.976692",
        "name": "Marvell Technology (MRVL)"
      },
      {
        "symbol": "MLEC",
        "regularMarketPrice": 6.83,
        "currency": "USD",
        "exchange": "NCM",
        "regularMarketChange": null,
        "regularMarketChangePercent": null,
        "regularMarketPreviousClose": 6.85,
        "regularMarketOpen": 6.85,
        "regularMarketDayHigh": null,
        "regularMarketDayLow": null,
        "timestamp": "2026-06-03T00:27:53.625865",
        "name": "Macom (MLEC)"
      }
    ],
    "期貨/指數期貨": [
      {
        "symbol": "ES=F",
        "regularMarketPrice": 0,
        "currency": "USD",
        "exchange": "CME",
        "regularMarketChange": null,
        "regularMarketChangePercent": null,
        "regularMarketPreviousClose": 0,
        "regularMarketOpen": 0,
        "regularMarketDayHigh": null,
        "regularMarketDayLow": null,
        "timestamp": "2026-06-03T00:27:54.175693",
        "name": "標普 500 期貨 (ES1!)"
      },
      {
        "symbol": "NQ=F",
        "regularMarketPrice": 0,
        "currency": "USD",
        "exchange": "CME",
        "regularMarketChange": null,
        "regularMarketChangePercent": null,
        "regularMarketPreviousClose": 0,
        "regularMarketOpen": 0,
        "regularMarketDayHigh": null,
        "regularMarketDayLow": null,
        "timestamp": "2026-06-03T00:27:54.848814",
        "name": "那斯達克 100 期貨 (NQ1!)"
      },
      {
        "symbol": "YM=F",
        "regularMarketPrice": 0,
        "currency": "USD",
        "exchange": "CBT",
        "regularMarketChange": null,
        "regularMarketChangePercent": null,
        "regularMarketPreviousClose": 0,
        "regularMarketOpen": 0,
        "regularMarketDayHigh": null,
        "regularMarketDayLow": null,
        "timestamp": "2026-06-03T00:27:55.347906",
        "name": "道瓊 期貨 (YM1!)"
      },
      {
        "symbol": "^VIX",
        "regularMarketPrice": null,
        "currency": "USD",
        "exchange": "CXI",
        "regularMarketChange": null,
        "regularMarketChangePercent": null,
        "regularMarketPreviousClose": null,
        "regularMarketOpen": 16.280000686645508,
        "regularMarketDayHigh": null,
        "regularMarketDayLow": null,
        "timestamp": "2026-06-03T00:27:55.705213",
        "name": "VIX 波動率指數"
      },
      {
        "symbol": "DX-Y.NYB",
        "regularMarketPrice": 0,
        "currency": "USD",
        "exchange": "NYB",
        "regularMarketChange": null,
        "regularMarketChangePercent": null,
        "regularMarketPreviousClose": 0,
        "regularMarketOpen": 0,
        "regularMarketDayHigh": null,
        "regularMarketDayLow": null,
        "timestamp": "2026-06-03T00:27:56.601816",
        "name": "美元指數 (DXY)"
      },
      {
        "symbol": "^TNX",
        "regularMarketPrice": null,
        "currency": "USD",
        "exchange": "CGI",
        "regularMarketChange": null,
        "regularMarketChangePercent": null,
        "regularMarketPreviousClose": null,
        "regularMarketOpen": 4.429999828338623,
        "regularMarketDayHigh": null,
        "regularMarketDayLow": null,
        "timestamp": "2026-06-03T00:27:56.877284",
        "name": "10 年期美債殖利率 (US10Y)"
      },
      {
        "symbol": "^SOX",
        "regularMarketPrice": null,
        "currency": "USD",
        "exchange": "NIM",
        "regularMarketChange": null,
        "regularMarketChangePercent": null,
        "regularMarketPreviousClose": null,
        "regularMarketOpen": 13242.7041015625,
        "regularMarketDayHigh": null,
        "regularMarketDayLow": null,
        "timestamp": "2026-06-03T00:27:57.305146",
        "name": "費城半導體指数 (SOX)"
      },
      {
        "symbol": "CL=F",
        "regularMarketPrice": 0,
        "currency": "USD",
        "exchange": "NYM",
        "regularMarketChange": null,
        "regularMarketChangePercent": null,
        "regularMarketPreviousClose": 0,
        "regularMarketOpen": 0,
        "regularMarketDayHigh": null,
        "regularMarketDayLow": null,
        "timestamp": "2026-06-03T00:27:58.043076",
        "name": "原油期貨 (CL1!)"
      },
      {
        "name": "法蘭克福指數 (TFX1!)",
        "symbol": "^FTX",
        "error": "'exchangeTimezoneName'"
      },
      {
        "symbol": "^IRX",
        "regularMarketPrice": null,
        "currency": "USD",
        "exchange": "CGI",
        "regularMarketChange": null,
        "regularMarketChangePercent": null,
        "regularMarketPreviousClose": null,
        "regularMarketOpen": 3.618000030517578,
        "regularMarketDayHigh": null,
        "regularMarketDayLow": null,
        "timestamp": "2026-06-03T00:27:59.465554",
        "name": "ICE 10 年期美債 (US10)"
      },
      {
        "name": "IXO 月期: IX0028",
        "symbol": "IX0028",
        "error": "'exchangeTimezoneName'"
      }
    ],
    "台股期貨": [
      {
        "symbol": "^TWII",
        "regularMarketPrice": null,
        "currency": "TWD",
        "exchange": "TAI",
        "regularMarketChange": null,
        "regularMarketChangePercent": null,
        "regularMarketPreviousClose": null,
        "regularMarketOpen": 45388.9296875,
        "regularMarketDayHigh": null,
        "regularMarketDayLow": null,
        "timestamp": "2026-06-03T00:28:01.197895",
        "name": "台指期"
      }
    ]
  }
}