{
  "retrieved_at": "2026-04-30T15:04:04.293040",
  "data": {
    "美股指數ETF": [
      {
        "symbol": "^DJI",
        "regularMarketPrice": null,
        "currency": "USD",
        "exchange": "DJI",
        "regularMarketChange": null,
        "regularMarketChangePercent": null,
        "regularMarketPreviousClose": null,
        "regularMarketOpen": 48762.9296875,
        "regularMarketDayHigh": null,
        "regularMarketDayLow": null,
        "timestamp": "2026-04-30T15:04:04.714246",
        "name": "道瓊指數 (DJI)"
      },
      {
        "symbol": "^NDX",
        "regularMarketPrice": null,
        "currency": "USD",
        "exchange": "NIM",
        "regularMarketChange": null,
        "regularMarketChangePercent": null,
        "regularMarketPreviousClose": null,
        "regularMarketOpen": 27328.986328125,
        "regularMarketDayHigh": null,
        "regularMarketDayLow": null,
        "timestamp": "2026-04-30T15:04:05.228744",
        "name": "那斯達克 100 (NDQ)"
      },
      {
        "symbol": "SPY",
        "regularMarketPrice": 714,
        "currency": "USD",
        "exchange": "PCX",
        "regularMarketChange": null,
        "regularMarketChangePercent": null,
        "regularMarketPreviousClose": 711.58,
        "regularMarketOpen": 712.8199999999999,
        "regularMarketDayHigh": null,
        "regularMarketDayLow": null,
        "timestamp": "2026-04-30T15:04:05.856990",
        "name": "SPY (標普 500 ETF)"
      },
      {
        "symbol": "VOO",
        "regularMarketPrice": 656.45,
        "currency": "USD",
        "exchange": "PCX",
        "regularMarketChange": null,
        "regularMarketChangePercent": null,
        "regularMarketPreviousClose": 654.24,
        "regularMarketOpen": 655.3050000000001,
        "regularMarketDayHigh": null,
        "regularMarketDayLow": null,
        "timestamp": "2026-04-30T15:04:06.568425",
        "name": "VOO (Vanguard S&P 500 ETF)"
      },
      {
        "symbol": "VTI",
        "regularMarketPrice": 351.85,
        "currency": "USD",
        "exchange": "PCX",
        "regularMarketChange": null,
        "regularMarketChangePercent": null,
        "regularMarketPreviousClose": 350.21,
        "regularMarketOpen": 350.82500000000005,
        "regularMarketDayHigh": null,
        "regularMarketDayLow": null,
        "timestamp": "2026-04-30T15:04:07.122379",
        "name": "VTI (Vanguard Total Stock Market)"
      },
      {
        "symbol": "QQQ",
        "regularMarketPrice": 662.93,
        "currency": "USD",
        "exchange": "NGM",
        "regularMarketChange": null,
        "regularMarketChangePercent": null,
        "regularMarketPreviousClose": 661.57,
        "regularMarketOpen": 663.7850000000001,
        "regularMarketDayHigh": null,
        "regularMarketDayLow": null,
        "timestamp": "2026-04-30T15:04:07.577283",
        "name": "QQQ (Invesco QQQ Trust)"
      }
    ],
    "美股個股 (科技+半導體)": [
      {
        "symbol": "NVDA",
        "regularMarketPrice": 201.93,
        "currency": "USD",
        "exchange": "NMS",
        "regularMarketChange": null,
        "regularMarketChangePercent": null,
        "regularMarketPreviousClose": 209.25,
        "regularMarketOpen": 209.965,
        "regularMarketDayHigh": null,
        "regularMarketDayLow": null,
        "timestamp": "2026-04-30T15:04:08.049339",
        "name": "輝達 (NVDA)"
      },
      {
        "symbol": "AMD",
        "regularMarketPrice": 347.66,
        "currency": "USD",
        "exchange": "NMS",
        "regularMarketChange": null,
        "regularMarketChangePercent": null,
        "regularMarketPreviousClose": 337.11,
        "regularMarketOpen": 341.26250000000005,
        "regularMarketDayHigh": null,
        "regularMarketDayLow": null,
        "timestamp": "2026-04-30T15:04:08.556925",
        "name": "AMD"
      },
      {
        "symbol": "AVGO",
        "regularMarketPrice": 411.35,
        "currency": "USD",
        "exchange": "NMS",
        "regularMarketChange": null,
        "regularMarketChangePercent": null,
        "regularMarketPreviousClose": 405.45,
        "regularMarketOpen": 412.385,
        "regularMarketDayHigh": null,
        "regularMarketDayLow": null,
        "timestamp": "2026-04-30T15:04:09.016770",
        "name": "博通 (AVGO)"
      },
      {
        "symbol": "MU",
        "regularMarketPrice": 509.02,
        "currency": "USD",
        "exchange": "NMS",
        "regularMarketChange": null,
        "regularMarketChangePercent": null,
        "regularMarketPreviousClose": 518.46,
        "regularMarketOpen": 524.1,
        "regularMarketDayHigh": null,
        "regularMarketDayLow": null,
        "timestamp": "2026-04-30T15:04:09.521679",
        "name": "美光 (MU)"
      },
      {
        "symbol": "TSLA",
        "regularMarketPrice": 377.34,
        "currency": "USD",
        "exchange": "NMS",
        "regularMarketChange": null,
        "regularMarketChangePercent": null,
        "regularMarketPreviousClose": 372.8,
        "regularMarketOpen": 372.2,
        "regularMarketDayHigh": null,
        "regularMarketDayLow": null,
        "timestamp": "2026-04-30T15:04:10.281828",
        "name": "特斯拉 (TSLA)"
      },
      {
        "symbol": "TSM",
        "regularMarketPrice": 390.89,
        "currency": "USD",
        "exchange": "NYQ",
        "regularMarketChange": null,
        "regularMarketChangePercent": null,
        "regularMarketPreviousClose": 393.83,
        "regularMarketOpen": 393.97749999999996,
        "regularMarketDayHigh": null,
        "regularMarketDayLow": null,
        "timestamp": "2026-04-30T15:04:10.812466",
        "name": "台積電 (TSM)"
      },
      {
        "symbol": "CRWV",
        "regularMarketPrice": 114.52,
        "currency": "USD",
        "exchange": "NMS",
        "regularMarketChange": null,
        "regularMarketChangePercent": null,
        "regularMarketPreviousClose": 114.19,
        "regularMarketOpen": 116.055,
        "regularMarketDayHigh": null,
        "regularMarketDayLow": null,
        "timestamp": "2026-04-30T15:04:11.228629",
        "name": "Crossriver Technologies (CRWV)"
      },
      {
        "symbol": "RKLB",
        "regularMarketPrice": 82.17,
        "currency": "USD",
        "exchange": "NCM",
        "regularMarketChange": null,
        "regularMarketChangePercent": null,
        "regularMarketPreviousClose": 77.02,
        "regularMarketOpen": 77.21000000000001,
        "regularMarketDayHigh": null,
        "regularMarketDayLow": null,
        "timestamp": "2026-04-30T15:04:11.474535",
        "name": "Rokla (RKLB)"
      },
      {
        "symbol": "AMZN",
        "regularMarketPrice": 259.69,
        "currency": "USD",
        "exchange": "NMS",
        "regularMarketChange": null,
        "regularMarketChangePercent": null,
        "regularMarketPreviousClose": 263.04,
        "regularMarketOpen": 270.805,
        "regularMarketDayHigh": null,
        "regularMarketDayLow": null,
        "timestamp": "2026-04-30T15:04:12.070872",
        "name": "亞馬遜 (AMZN)"
      },
      {
        "symbol": "SNDK",
        "regularMarketPrice": 1096.82,
        "currency": "USD",
        "exchange": "NMS",
        "regularMarketChange": null,
        "regularMarketChangePercent": null,
        "regularMarketPreviousClose": 1064.21,
        "regularMarketOpen": 1099.6750000000002,
        "regularMarketDayHigh": null,
        "regularMarketDayLow": null,
        "timestamp": "2026-04-30T15:04:12.734075",
        "name": "Sandisk (SNDK)"
      },
      {
        "symbol": "AAPL",
        "regularMarketPrice": 270.97,
        "currency": "USD",
        "exchange": "NMS",
        "regularMarketChange": null,
        "regularMarketChangePercent": null,
        "regularMarketPreviousClose": 270.17,
        "regularMarketOpen": 270.47,
        "regularMarketDayHigh": null,
        "regularMarketDayLow": null,
        "timestamp": "2026-04-30T15:04:13.418160",
        "name": "蘋果 (AAPL)"
      },
      {
        "symbol": "ORCL",
        "regularMarketPrice": 162.37,
        "currency": "USD",
        "exchange": "NYQ",
        "regularMarketChange": null,
        "regularMarketChangePercent": null,
        "regularMarketPreviousClose": 163.83,
        "regularMarketOpen": 162.445,
        "regularMarketDayHigh": null,
        "regularMarketDayLow": null,
        "timestamp": "2026-04-30T15:04:13.964463",
        "name": "甲骨文 (ORCL)"
      },
      {
        "symbol": "ARM",
        "regularMarketPrice": 208.57,
        "currency": "USD",
        "exchange": "NMS",
        "regularMarketChange": null,
        "regularMarketChangePercent": null,
        "regularMarketPreviousClose": 201.69,
        "regularMarketOpen": 202.945,
        "regularMarketDayHigh": null,
        "regularMarketDayLow": null,
        "timestamp": "2026-04-30T15:04:14.617193",
        "name": "Arm (ARM)"
      },
      {
        "symbol": "GOOG",
        "regularMarketPrice": 370.28,
        "currency": "USD",
        "exchange": "NMS",
        "regularMarketChange": null,
        "regularMarketChangePercent": null,
        "regularMarketPreviousClose": 347.31,
        "regularMarketOpen": 370.8025,
        "regularMarketDayHigh": null,
        "regularMarketDayLow": null,
        "timestamp": "2026-04-30T15:04:15.006833",
        "name": "谷歌 (GOOG)"
      },
      {
        "symbol": "META",
        "regularMarketPrice": 608.4,
        "currency": "USD",
        "exchange": "NMS",
        "regularMarketChange": null,
        "regularMarketChangePercent": null,
        "regularMarketPreviousClose": 669.12,
        "regularMarketOpen": 622.83,
        "regularMarketDayHigh": null,
        "regularMarketDayLow": null,
        "timestamp": "2026-04-30T15:04:15.526730",
        "name": "Meta (META)"
      },
      {
        "symbol": "MSFT",
        "regularMarketPrice": 406.34,
        "currency": "USD",
        "exchange": "NMS",
        "regularMarketChange": null,
        "regularMarketChangePercent": null,
        "regularMarketPreviousClose": 424.46,
        "regularMarketOpen": 415.555,
        "regularMarketDayHigh": null,
        "regularMarketDayLow": null,
        "timestamp": "2026-04-30T15:04:15.981411",
        "name": "微軟 (MSFT)"
      },
      {
        "symbol": "PLTR",
        "regularMarketPrice": 139.98,
        "currency": "USD",
        "exchange": "NMS",
        "regularMarketChange": null,
        "regularMarketChangePercent": null,
        "regularMarketPreviousClose": 137.97,
        "regularMarketOpen": 137.9025,
        "regularMarketDayHigh": null,
        "regularMarketDayLow": null,
        "timestamp": "2026-04-30T15:04:16.299240",
        "name": "Palantir (PLTR)"
      },
      {
        "symbol": "ASML",
        "regularMarketPrice": 1422.84,
        "currency": "USD",
        "exchange": "NMS",
        "regularMarketChange": null,
        "regularMarketChangePercent": null,
        "regularMarketPreviousClose": 1394.08,
        "regularMarketOpen": 1404.505,
        "regularMarketDayHigh": null,
        "regularMarketDayLow": null,
        "timestamp": "2026-04-30T15:04:16.871834",
        "name": "ASML"
      },
      {
        "symbol": "COST",
        "regularMarketPrice": 1009.86,
        "currency": "USD",
        "exchange": "NMS",
        "regularMarketChange": null,
        "regularMarketChangePercent": null,
        "regularMarketPreviousClose": 998.67,
        "regularMarketOpen": 994.955,
        "regularMarketDayHigh": null,
        "regularMarketDayLow": null,
        "timestamp": "2026-04-30T15:04:17.579073",
        "name": "Costco (COST)"
      },
      {
        "symbol": "MRVL",
        "regularMarketPrice": 162.76,
        "currency": "USD",
        "exchange": "NMS",
        "regularMarketChange": null,
        "regularMarketChangePercent": null,
        "regularMarketPreviousClose": 156.57,
        "regularMarketOpen": 159.305,
        "regularMarketDayHigh": null,
        "regularMarketDayLow": null,
        "timestamp": "2026-04-30T15:04:18.473899",
        "name": "Marvell Technology (MRVL)"
      },
      {
        "symbol": "MLEC",
        "regularMarketPrice": 10.19,
        "currency": "USD",
        "exchange": "NCM",
        "regularMarketChange": null,
        "regularMarketChangePercent": null,
        "regularMarketPreviousClose": 8.99,
        "regularMarketOpen": 8.735,
        "regularMarketDayHigh": null,
        "regularMarketDayLow": null,
        "timestamp": "2026-04-30T15:04:18.867569",
        "name": "Macom (MLEC)"
      }
    ],
    "期貨/指數期貨": [
      {
        "symbol": "ES=F",
        "regularMarketPrice": 0,
        "currency": "USD",
        "exchange": "CME",
        "regularMarketChange": null,
        "regularMarketChangePercent": null,
        "regularMarketPreviousClose": 0,
        "regularMarketOpen": 0,
        "regularMarketDayHigh": null,
        "regularMarketDayLow": null,
        "timestamp": "2026-04-30T15:04:22.288391",
        "name": "標普 500 期貨 (ES1!)"
      },
      {
        "symbol": "NQ=F",
        "regularMarketPrice": 0,
        "currency": "USD",
        "exchange": "CME",
        "regularMarketChange": null,
        "regularMarketChangePercent": null,
        "regularMarketPreviousClose": 0,
        "regularMarketOpen": 0,
        "regularMarketDayHigh": null,
        "regularMarketDayLow": null,
        "timestamp": "2026-04-30T15:04:25.635886",
        "name": "那斯達克 100 期貨 (NQ1!)"
      },
      {
        "symbol": "YM=F",
        "regularMarketPrice": 0,
        "currency": "USD",
        "exchange": "CBT",
        "regularMarketChange": null,
        "regularMarketChangePercent": null,
        "regularMarketPreviousClose": 0,
        "regularMarketOpen": 0,
        "regularMarketDayHigh": null,
        "regularMarketDayLow": null,
        "timestamp": "2026-04-30T15:04:29.100830",
        "name": "道瓊 期貨 (YM1!)"
      },
      {
        "symbol": "^VIX",
        "regularMarketPrice": null,
        "currency": "USD",
        "exchange": "CXI",
        "regularMarketChange": null,
        "regularMarketChangePercent": null,
        "regularMarketPreviousClose": null,
        "regularMarketOpen": 18.68000030517578,
        "regularMarketDayHigh": null,
        "regularMarketDayLow": null,
        "timestamp": "2026-04-30T15:04:29.412098",
        "name": "VIX 波動率指數"
      },
      {
        "symbol": "DX-Y.NYB",
        "regularMarketPrice": 0,
        "currency": "USD",
        "exchange": "NYB",
        "regularMarketChange": null,
        "regularMarketChangePercent": null,
        "regularMarketPreviousClose": 0,
        "regularMarketOpen": 0,
        "regularMarketDayHigh": null,
        "regularMarketDayLow": null,
        "timestamp": "2026-04-30T15:04:33.804942",
        "name": "美元指數 (DXY)"
      },
      {
        "symbol": "^TNX",
        "regularMarketPrice": null,
        "currency": "USD",
        "exchange": "CGI",
        "regularMarketChange": null,
        "regularMarketChangePercent": null,
        "regularMarketPreviousClose": null,
        "regularMarketOpen": 4.3919997215271,
        "regularMarketDayHigh": null,
        "regularMarketDayLow": null,
        "timestamp": "2026-04-30T15:04:33.957513",
        "name": "10 年期美債殖利率 (US10Y)"
      },
      {
        "symbol": "^SOX",
        "regularMarketPrice": null,
        "currency": "USD",
        "exchange": "NIM",
        "regularMarketChange": null,
        "regularMarketChangePercent": null,
        "regularMarketPreviousClose": null,
        "regularMarketOpen": 10387.83984375,
        "regularMarketDayHigh": null,
        "regularMarketDayLow": null,
        "timestamp": "2026-04-30T15:04:34.338522",
        "name": "費城半導體指数 (SOX)"
      },
      {
        "symbol": "CL=F",
        "regularMarketPrice": 0,
        "currency": "USD",
        "exchange": "NYM",
        "regularMarketChange": null,
        "regularMarketChangePercent": null,
        "regularMarketPreviousClose": 0,
        "regularMarketOpen": 0,
        "regularMarketDayHigh": null,
        "regularMarketDayLow": null,
        "timestamp": "2026-04-30T15:04:37.780776",
        "name": "原油期貨 (CL1!)"
      },
      {
        "name": "法蘭克福指數 (TFX1!)",
        "symbol": "^FTX",
        "error": "'PriceHistory' object has no attribute '_dividends'"
      },
      {
        "symbol": "^IRX",
        "regularMarketPrice": null,
        "currency": "USD",
        "exchange": "CGI",
        "regularMarketChange": null,
        "regularMarketChangePercent": null,
        "regularMarketPreviousClose": null,
        "regularMarketOpen": 3.5849997997283936,
        "regularMarketDayHigh": null,
        "regularMarketDayLow": null,
        "timestamp": "2026-04-30T15:04:38.859791",
        "name": "ICE 10 年期美債 (US10)"
      },
      {
        "name": "IXO 月期: IX0028",
        "symbol": "IX0028",
        "error": "'PriceHistory' object has no attribute '_dividends'"
      }
    ],
    "台股期貨": [
      {
        "symbol": "^TWII",
        "regularMarketPrice": null,
        "currency": "TWD",
        "exchange": "TAI",
        "regularMarketChange": null,
        "regularMarketChangePercent": null,
        "regularMarketPreviousClose": null,
        "regularMarketOpen": 39571.4609375,
        "regularMarketDayHigh": null,
        "regularMarketDayLow": null,
        "timestamp": "2026-04-30T15:04:40.102528",
        "name": "台指期"
      }
    ]
  }
}