{
  "retrieved_at": "2026-05-26T18:21:37.600975",
  "data": {
    "美股指數ETF": [
      {
        "symbol": "^DJI",
        "regularMarketPrice": null,
        "currency": "USD",
        "exchange": "DJI",
        "regularMarketChange": null,
        "regularMarketChangePercent": null,
        "regularMarketPreviousClose": null,
        "regularMarketOpen": 50686.1484375,
        "regularMarketDayHigh": null,
        "regularMarketDayLow": null,
        "timestamp": "2026-05-26T18:21:37.842330",
        "name": "道瓊指數 (DJI)"
      },
      {
        "symbol": "^NDX",
        "regularMarketPrice": null,
        "currency": "USD",
        "exchange": "NIM",
        "regularMarketChange": null,
        "regularMarketChangePercent": null,
        "regularMarketPreviousClose": null,
        "regularMarketOpen": 29854.58203125,
        "regularMarketDayHigh": null,
        "regularMarketDayLow": null,
        "timestamp": "2026-05-26T18:21:38.048102",
        "name": "那斯達克 100 (NDQ)"
      },
      {
        "symbol": "SPY",
        "regularMarketPrice": null,
        "currency": "USD",
        "exchange": "PCX",
        "regularMarketChange": null,
        "regularMarketChangePercent": null,
        "regularMarketPreviousClose": null,
        "regularMarketOpen": 750.010009765625,
        "regularMarketDayHigh": null,
        "regularMarketDayLow": null,
        "timestamp": "2026-05-26T18:21:38.366473",
        "name": "SPY (標普 500 ETF)"
      },
      {
        "symbol": "VOO",
        "regularMarketPrice": null,
        "currency": "USD",
        "exchange": "PCX",
        "regularMarketChange": null,
        "regularMarketChangePercent": null,
        "regularMarketPreviousClose": null,
        "regularMarketOpen": 689.6500244140625,
        "regularMarketDayHigh": null,
        "regularMarketDayLow": null,
        "timestamp": "2026-05-26T18:21:38.737778",
        "name": "VOO (Vanguard S&P 500 ETF)"
      },
      {
        "symbol": "VTI",
        "regularMarketPrice": null,
        "currency": "USD",
        "exchange": "PCX",
        "regularMarketChange": null,
        "regularMarketChangePercent": null,
        "regularMarketPreviousClose": null,
        "regularMarketOpen": 368.9800109863281,
        "regularMarketDayHigh": null,
        "regularMarketDayLow": null,
        "timestamp": "2026-05-26T18:21:39.151954",
        "name": "VTI (Vanguard Total Stock Market)"
      },
      {
        "symbol": "QQQ",
        "regularMarketPrice": null,
        "currency": "USD",
        "exchange": "NGM",
        "regularMarketChange": null,
        "regularMarketChangePercent": null,
        "regularMarketPreviousClose": null,
        "regularMarketOpen": 726.0250244140625,
        "regularMarketDayHigh": null,
        "regularMarketDayLow": null,
        "timestamp": "2026-05-26T18:21:39.402847",
        "name": "QQQ (Invesco QQQ Trust)"
      }
    ],
    "美股個股 (科技+半導體)": [
      {
        "symbol": "NVDA",
        "regularMarketPrice": null,
        "currency": "USD",
        "exchange": "NMS",
        "regularMarketChange": null,
        "regularMarketChangePercent": null,
        "regularMarketPreviousClose": null,
        "regularMarketOpen": 216.57749938964844,
        "regularMarketDayHigh": null,
        "regularMarketDayLow": null,
        "timestamp": "2026-05-26T18:21:39.676996",
        "name": "輝達 (NVDA)"
      },
      {
        "symbol": "AMD",
        "regularMarketPrice": null,
        "currency": "USD",
        "exchange": "NMS",
        "regularMarketChange": null,
        "regularMarketChangePercent": null,
        "regularMarketPreviousClose": null,
        "regularMarketOpen": 484.70599365234375,
        "regularMarketDayHigh": null,
        "regularMarketDayLow": null,
        "timestamp": "2026-05-26T18:21:39.915675",
        "name": "AMD"
      },
      {
        "symbol": "AVGO",
        "regularMarketPrice": null,
        "currency": "USD",
        "exchange": "NMS",
        "regularMarketChange": null,
        "regularMarketChangePercent": null,
        "regularMarketPreviousClose": null,
        "regularMarketOpen": 418.7200012207031,
        "regularMarketDayHigh": null,
        "regularMarketDayLow": null,
        "timestamp": "2026-05-26T18:21:40.226766",
        "name": "博通 (AVGO)"
      },
      {
        "symbol": "MU",
        "regularMarketPrice": null,
        "currency": "USD",
        "exchange": "NMS",
        "regularMarketChange": null,
        "regularMarketChangePercent": null,
        "regularMarketPreviousClose": null,
        "regularMarketOpen": 820.5,
        "regularMarketDayHigh": null,
        "regularMarketDayLow": null,
        "timestamp": "2026-05-26T18:21:40.516258",
        "name": "美光 (MU)"
      },
      {
        "symbol": "TSLA",
        "regularMarketPrice": null,
        "currency": "USD",
        "exchange": "NMS",
        "regularMarketChange": null,
        "regularMarketChangePercent": null,
        "regularMarketPreviousClose": null,
        "regularMarketOpen": 430.0199890136719,
        "regularMarketDayHigh": null,
        "regularMarketDayLow": null,
        "timestamp": "2026-05-26T18:21:40.785759",
        "name": "特斯拉 (TSLA)"
      },
      {
        "symbol": "TSM",
        "regularMarketPrice": null,
        "currency": "USD",
        "exchange": "NYQ",
        "regularMarketChange": null,
        "regularMarketChangePercent": null,
        "regularMarketPreviousClose": null,
        "regularMarketOpen": 413.1199951171875,
        "regularMarketDayHigh": null,
        "regularMarketDayLow": null,
        "timestamp": "2026-05-26T18:21:41.075347",
        "name": "台積電 (TSM)"
      },
      {
        "symbol": "CRWV",
        "regularMarketPrice": null,
        "currency": "USD",
        "exchange": "NMS",
        "regularMarketChange": null,
        "regularMarketChangePercent": null,
        "regularMarketPreviousClose": null,
        "regularMarketOpen": 108.23999786376953,
        "regularMarketDayHigh": null,
        "regularMarketDayLow": null,
        "timestamp": "2026-05-26T18:21:41.446406",
        "name": "Crossriver Technologies (CRWV)"
      },
      {
        "symbol": "RKLB",
        "regularMarketPrice": null,
        "currency": "USD",
        "exchange": "NMS",
        "regularMarketChange": null,
        "regularMarketChangePercent": null,
        "regularMarketPreviousClose": null,
        "regularMarketOpen": 141.96499633789062,
        "regularMarketDayHigh": null,
        "regularMarketDayLow": null,
        "timestamp": "2026-05-26T18:21:41.778979",
        "name": "Rokla (RKLB)"
      },
      {
        "symbol": "AMZN",
        "regularMarketPrice": null,
        "currency": "USD",
        "exchange": "NMS",
        "regularMarketChange": null,
        "regularMarketChangePercent": null,
        "regularMarketPreviousClose": null,
        "regularMarketOpen": 267.57501220703125,
        "regularMarketDayHigh": null,
        "regularMarketDayLow": null,
        "timestamp": "2026-05-26T18:21:42.256195",
        "name": "亞馬遜 (AMZN)"
      },
      {
        "symbol": "SNDK",
        "regularMarketPrice": null,
        "currency": "USD",
        "exchange": "NMS",
        "regularMarketChange": null,
        "regularMarketChangePercent": null,
        "regularMarketPreviousClose": null,
        "regularMarketOpen": 1535.64501953125,
        "regularMarketDayHigh": null,
        "regularMarketDayLow": null,
        "timestamp": "2026-05-26T18:21:42.701210",
        "name": "Sandisk (SNDK)"
      },
      {
        "symbol": "AAPL",
        "regularMarketPrice": null,
        "currency": "USD",
        "exchange": "NMS",
        "regularMarketChange": null,
        "regularMarketChangePercent": null,
        "regularMarketPreviousClose": null,
        "regularMarketOpen": 309.3999938964844,
        "regularMarketDayHigh": null,
        "regularMarketDayLow": null,
        "timestamp": "2026-05-26T18:21:43.030434",
        "name": "蘋果 (AAPL)"
      },
      {
        "symbol": "ORCL",
        "regularMarketPrice": null,
        "currency": "USD",
        "exchange": "NYQ",
        "regularMarketChange": null,
        "regularMarketChangePercent": null,
        "regularMarketPreviousClose": null,
        "regularMarketOpen": 193.3000030517578,
        "regularMarketDayHigh": null,
        "regularMarketDayLow": null,
        "timestamp": "2026-05-26T18:21:43.435242",
        "name": "甲骨文 (ORCL)"
      },
      {
        "symbol": "ARM",
        "regularMarketPrice": null,
        "currency": "USD",
        "exchange": "NMS",
        "regularMarketChange": null,
        "regularMarketChangePercent": null,
        "regularMarketPreviousClose": null,
        "regularMarketOpen": 317.32501220703125,
        "regularMarketDayHigh": null,
        "regularMarketDayLow": null,
        "timestamp": "2026-05-26T18:21:43.663883",
        "name": "Arm (ARM)"
      },
      {
        "symbol": "GOOG",
        "regularMarketPrice": null,
        "currency": "USD",
        "exchange": "NMS",
        "regularMarketChange": null,
        "regularMarketChangePercent": null,
        "regularMarketPreviousClose": null,
        "regularMarketOpen": 380.9949951171875,
        "regularMarketDayHigh": null,
        "regularMarketDayLow": null,
        "timestamp": "2026-05-26T18:21:43.878659",
        "name": "谷歌 (GOOG)"
      },
      {
        "symbol": "META",
        "regularMarketPrice": null,
        "currency": "USD",
        "exchange": "NMS",
        "regularMarketChange": null,
        "regularMarketChangePercent": null,
        "regularMarketPreviousClose": null,
        "regularMarketOpen": 609.5999755859375,
        "regularMarketDayHigh": null,
        "regularMarketDayLow": null,
        "timestamp": "2026-05-26T18:21:44.151288",
        "name": "Meta (META)"
      },
      {
        "symbol": "MSFT",
        "regularMarketPrice": null,
        "currency": "USD",
        "exchange": "NMS",
        "regularMarketChange": null,
        "regularMarketChangePercent": null,
        "regularMarketPreviousClose": null,
        "regularMarketOpen": 416.42999267578125,
        "regularMarketDayHigh": null,
        "regularMarketDayLow": null,
        "timestamp": "2026-05-26T18:21:44.499374",
        "name": "微軟 (MSFT)"
      },
      {
        "symbol": "PLTR",
        "regularMarketPrice": null,
        "currency": "USD",
        "exchange": "NMS",
        "regularMarketChange": null,
        "regularMarketChangePercent": null,
        "regularMarketPreviousClose": null,
        "regularMarketOpen": 136.1699981689453,
        "regularMarketDayHigh": null,
        "regularMarketDayLow": null,
        "timestamp": "2026-05-26T18:21:44.772816",
        "name": "Palantir (PLTR)"
      },
      {
        "symbol": "ASML",
        "regularMarketPrice": null,
        "currency": "USD",
        "exchange": "NMS",
        "regularMarketChange": null,
        "regularMarketChangePercent": null,
        "regularMarketPreviousClose": null,
        "regularMarketOpen": 1641.9749755859375,
        "regularMarketDayHigh": null,
        "regularMarketDayLow": null,
        "timestamp": "2026-05-26T18:21:45.017699",
        "name": "ASML"
      },
      {
        "symbol": "COST",
        "regularMarketPrice": null,
        "currency": "USD",
        "exchange": "NMS",
        "regularMarketChange": null,
        "regularMarketChangePercent": null,
        "regularMarketPreviousClose": null,
        "regularMarketOpen": 1025.0999755859375,
        "regularMarketDayHigh": null,
        "regularMarketDayLow": null,
        "timestamp": "2026-05-26T18:21:45.327032",
        "name": "Costco (COST)"
      },
      {
        "symbol": "MRVL",
        "regularMarketPrice": null,
        "currency": "USD",
        "exchange": "NMS",
        "regularMarketChange": null,
        "regularMarketChangePercent": null,
        "regularMarketPreviousClose": null,
        "regularMarketOpen": 211.2449951171875,
        "regularMarketDayHigh": null,
        "regularMarketDayLow": null,
        "timestamp": "2026-05-26T18:21:45.735110",
        "name": "Marvell Technology (MRVL)"
      },
      {
        "symbol": "MLEC",
        "regularMarketPrice": null,
        "currency": "USD",
        "exchange": "NCM",
        "regularMarketChange": null,
        "regularMarketChangePercent": null,
        "regularMarketPreviousClose": null,
        "regularMarketOpen": 7.730000019073486,
        "regularMarketDayHigh": null,
        "regularMarketDayLow": null,
        "timestamp": "2026-05-26T18:21:46.128751",
        "name": "Macom (MLEC)"
      }
    ],
    "期貨/指數期貨": [
      {
        "symbol": "ES=F",
        "regularMarketPrice": null,
        "currency": "USD",
        "exchange": "CME",
        "regularMarketChange": null,
        "regularMarketChangePercent": null,
        "regularMarketPreviousClose": null,
        "regularMarketOpen": 7519.0,
        "regularMarketDayHigh": null,
        "regularMarketDayLow": null,
        "timestamp": "2026-05-26T18:21:46.386108",
        "name": "標普 500 期貨 (ES1!)"
      },
      {
        "symbol": "NQ=F",
        "regularMarketPrice": null,
        "currency": "USD",
        "exchange": "CME",
        "regularMarketChange": null,
        "regularMarketChangePercent": null,
        "regularMarketPreviousClose": null,
        "regularMarketOpen": 29676.25,
        "regularMarketDayHigh": null,
        "regularMarketDayLow": null,
        "timestamp": "2026-05-26T18:21:46.813001",
        "name": "那斯達克 100 期貨 (NQ1!)"
      },
      {
        "symbol": "YM=F",
        "regularMarketPrice": null,
        "currency": "USD",
        "exchange": "CBT",
        "regularMarketChange": null,
        "regularMarketChangePercent": null,
        "regularMarketPreviousClose": null,
        "regularMarketOpen": 50776.0,
        "regularMarketDayHigh": null,
        "regularMarketDayLow": null,
        "timestamp": "2026-05-26T18:21:47.057260",
        "name": "道瓊 期貨 (YM1!)"
      },
      {
        "symbol": "^VIX",
        "regularMarketPrice": null,
        "currency": "USD",
        "exchange": "CXI",
        "regularMarketChange": null,
        "regularMarketChangePercent": null,
        "regularMarketPreviousClose": null,
        "regularMarketOpen": 16.920000076293945,
        "regularMarketDayHigh": null,
        "regularMarketDayLow": null,
        "timestamp": "2026-05-26T18:21:47.239464",
        "name": "VIX 波動率指數"
      },
      {
        "symbol": "DX-Y.NYB",
        "regularMarketPrice": null,
        "currency": "USD",
        "exchange": "NYB",
        "regularMarketChange": null,
        "regularMarketChangePercent": null,
        "regularMarketPreviousClose": null,
        "regularMarketOpen": 98.98799896240234,
        "regularMarketDayHigh": null,
        "regularMarketDayLow": null,
        "timestamp": "2026-05-26T18:21:47.517631",
        "name": "美元指數 (DXY)"
      },
      {
        "symbol": "^TNX",
        "regularMarketPrice": null,
        "currency": "USD",
        "exchange": "CGI",
        "regularMarketChange": null,
        "regularMarketChangePercent": null,
        "regularMarketPreviousClose": null,
        "regularMarketOpen": 4.488999843597412,
        "regularMarketDayHigh": null,
        "regularMarketDayLow": null,
        "timestamp": "2026-05-26T18:21:47.754798",
        "name": "10 年期美債殖利率 (US10Y)"
      },
      {
        "symbol": "^SOX",
        "regularMarketPrice": null,
        "currency": "USD",
        "exchange": "NIM",
        "regularMarketChange": null,
        "regularMarketChangePercent": null,
        "regularMarketPreviousClose": null,
        "regularMarketOpen": 12616.630859375,
        "regularMarketDayHigh": null,
        "regularMarketDayLow": null,
        "timestamp": "2026-05-26T18:21:47.966325",
        "name": "費城半導體指数 (SOX)"
      },
      {
        "symbol": "CL=F",
        "regularMarketPrice": null,
        "currency": "USD",
        "exchange": "NYM",
        "regularMarketChange": null,
        "regularMarketChangePercent": null,
        "regularMarketPreviousClose": null,
        "regularMarketOpen": 93.87999725341797,
        "regularMarketDayHigh": null,
        "regularMarketDayLow": null,
        "timestamp": "2026-05-26T18:21:48.190020",
        "name": "原油期貨 (CL1!)"
      },
      {
        "name": "法蘭克福指數 (TFX1!)",
        "symbol": "^FTX",
        "error": "'exchangeTimezoneName'"
      },
      {
        "symbol": "^IRX",
        "regularMarketPrice": null,
        "currency": "USD",
        "exchange": "CGI",
        "regularMarketChange": null,
        "regularMarketChangePercent": null,
        "regularMarketPreviousClose": null,
        "regularMarketOpen": 3.5799999237060547,
        "regularMarketDayHigh": null,
        "regularMarketDayLow": null,
        "timestamp": "2026-05-26T18:21:48.833372",
        "name": "ICE 10 年期美債 (US10)"
      },
      {
        "name": "IXO 月期: IX0028",
        "symbol": "IX0028",
        "error": "'exchangeTimezoneName'"
      }
    ],
    "台股期貨": [
      {
        "symbol": "^TWII",
        "regularMarketPrice": null,
        "currency": "TWD",
        "exchange": "TAI",
        "regularMarketChange": null,
        "regularMarketChangePercent": null,
        "regularMarketPreviousClose": null,
        "regularMarketOpen": 43708.890625,
        "regularMarketDayHigh": null,
        "regularMarketDayLow": null,
        "timestamp": "2026-05-26T18:21:49.639319",
        "name": "台指期"
      }
    ]
  }
}