{
  "retrieved_at": "2026-03-26T23:01:21.891486",
  "feeds": [
    {
      "name": "Reuters Top News",
      "language": "en",
      "url": "https://feeds.reuters.com/reuters/topNews",
      "items": []
    },
    {
      "name": "BBC News - World",
      "language": "en",
      "url": "https://feeds.bbci.co.uk/news/world/rss.xml",
      "items": [
        {
          "title": "Zelensky visits Saudi Arabia after offering Ukraine's drone expertise",
          "summary": "There is renewed urgency for Ukraine to get a drone deal done, as the US increasingly focuses on Iran.",
          "link": "https://www.bbc.com/news/articles/cx2r4wxdw3no?at_medium=RSS&at_campaign=rss",
          "published": "Thu, 26 Mar 2026 18:24:13 GMT",
          "keywords": [
            "AI"
          ]
        },
        {
          "title": "Rationing power and diluting petrol - how African countries are coping with effects of Iran war",
          "summary": "The disruption in oil supplies has caused shortages and concerns in several African countries.",
          "link": "https://www.bbc.com/news/articles/cq8wkq1n9epo?at_medium=RSS&at_campaign=rss",
          "published": "Thu, 26 Mar 2026 17:57:41 GMT",
          "keywords": []
        },
        {
          "title": "US prosecutors argue Maduro 'plundered' Venezuelan wealth in court battle over legal fees",
          "summary": "A judge said the right to defence was paramount as prosecutors argued the couple should not be able to use Venezuelan funds to pay lawyers.",
          "link": "https://www.bbc.com/news/articles/c4g8wxyq7v5o?at_medium=RSS&at_campaign=rss",
          "published": "Thu, 26 Mar 2026 18:49:46 GMT",
          "keywords": [
            "AI"
          ]
        }
      ]
    },
    {
      "name": "AP News",
      "language": "en",
      "url": "https://apnews.com/index.rss",
      "items": []
    },
    {
      "name": "CNN World",
      "language": "en",
      "url": "http://rss.cnn.com/rss/cnn_world.rss",
      "items": [
        {
          "title": "Markets digest bank earnings after recent turmoil",
          "summary": "",
          "link": "https://www.cnn.com/business/live-news/stock-market-bank-earnings/index.html",
          "published": "Fri, 14 Apr 2023 20:00:28 GMT",
          "keywords": []
        },
        {
          "title": "Still haven't filed your taxes? Here's what you need to know",
          "summary": "So far this tax season, the IRS has received more than 90 million income tax returns for 2022.",
          "link": "https://www.cnn.com/2023/04/13/success/tax-filing-tips/index.html",
          "published": "Fri, 14 Apr 2023 20:07:40 GMT",
          "keywords": []
        },
        {
          "title": "Retail spending fell in March as consumers pull back",
          "summary": "Spending at US retailers fell in March as consumers pulled back amid recessionary fears fueled by the banking crisis.",
          "link": "https://www.cnn.com/2023/04/14/economy/march-retail-sales/index.html",
          "published": "Fri, 14 Apr 2023 14:29:52 GMT",
          "keywords": [
            "AI"
          ]
        }
      ]
    },
    {
      "name": "CNN Top Stories",
      "language": "en",
      "url": "http://rss.cnn.com/rss/cnn_topstories.rss",
      "items": [
        {
          "title": "Some on-air claims about Dominion Voting Systems were false, Fox News acknowledges in statement after deal is announced",
          "summary": "",
          "link": "https://www.cnn.com/business/live-news/fox-news-dominion-trial-04-18-23/index.html",
          "published": "Wed, 19 Apr 2023 12:44:51 GMT",
          "keywords": [
            "AI"
          ]
        },
        {
          "title": "Dominion still has pending lawsuits against election deniers such as Rudy Giuliani and Sidney Powell",
          "summary": "",
          "link": "https://www.cnn.com/business/live-news/fox-news-dominion-trial-04-18-23/h_8d51e3ae2714edaa0dace837305d03b8",
          "published": "",
          "keywords": [
            "AI"
          ]
        },
        {
          "title": "Here are the 20 specific Fox broadcasts and tweets Dominion says were defamatory",
          "summary": "• Fox-Dominion trial delay 'is not unusual,' judge says • Fox News' defamation battle isn't stopping Trump's election lies",
          "link": "https://www.cnn.com/2023/04/17/media/dominion-fox-news-allegations/index.html",
          "published": "Mon, 17 Apr 2023 16:01:11 GMT",
          "keywords": []
        }
      ]
    },
    {
      "name": "自由時報國際",
      "language": "zh",
      "url": "https://news.ltn.com.tw/rss/world.xml",
      "items": [
        {
          "title": "川普宣布延後攻擊伊朗能源設施 期限至4/6",
          "summary": "中東局勢動盪，美國總統川普稍早發文稱與伊朗的談判進展非常順利，並決定再次延後針對伊朗能源設施的軍事打擊，期限將延到2026年4月6日晚上8時（美東時間），暫停行動為期10天，盼為...…",
          "link": "https://news.ltn.com.tw/news/world/breakingnews/5384128",
          "published": "Fri, 27 Mar 2026 06:49:24 +0800",
          "keywords": []
        },
        {
          "title": "國際奧會禁跨性別女運動員參賽 白宮表態力挺",
          "summary": "在2028年洛杉磯奧林匹克運動會登場前，國際奧林匹克委員會（IOC）26日禁止跨性別女性參加女性賽事，此舉隨即獲得白宮的讚賞。  首位擔任國際奧會主席的女性柯芬特里（Ki...…",
          "link": "https://news.ltn.com.tw/news/world/breakingnews/5384102",
          "published": "Fri, 27 Mar 2026 06:46:52 +0800",
          "keywords": []
        },
        {
          "title": "存在國安風險 英國政府否決中國風機設廠計畫",
          "summary": "中國再生能源公司「明陽智慧能源集團股份公司」（Ming Yang Smart Energy）表示，該公司在蘇格蘭高地開設英國最大風力發電機製造廠的計畫，已遭英國政府否決，理由...…",
          "link": "https://news.ltn.com.tw/news/world/breakingnews/5384098",
          "published": "Fri, 27 Mar 2026 06:44:40 +0800",
          "keywords": []
        }
      ]
    },
    {
      "name": "聯合報國際",
      "language": "zh",
      "url": "https://udn.com/rssfeed/news/1001/6649/1?type=2",
      "items": []
    }
  ]
}